LICENSE.txt
MANIFEST.in
README.md
setup.py
practichem_biodetector/__init__.py
practichem_biodetector/biodetector.py
practichem_biodetector.egg-info/PKG-INFO
practichem_biodetector.egg-info/SOURCES.txt
practichem_biodetector.egg-info/dependency_links.txt
practichem_biodetector.egg-info/requires.txt
practichem_biodetector.egg-info/top_level.txt
practichem_biodetector.egg-info/zip-safe